[
    {
        "key":"04",
        "name":"4月",
        "value":"0",
        "unit":""
    },
    {
        "key":"05",
        "name":"5月",
        "value":"0",
        "unit":""
    },
    {
        "key":"06",
        "name":"6月",
        "value":"0",
        "unit":""
    },
    {
        "key":"07",
        "name":"7月",
        "value":"0",
        "unit":""
    },
    {
        "key":"08",
        "name":"8月",
        "value":"0",
        "unit":""
    },
    {
        "key":"09",
        "name":"9月",
        "value":"0",
        "unit":""
    },
    {
        "key":"10",
        "name":"10月",
        "value":"1",
        "unit":""
    },
    {
        "key":"11",
        "name":"11月",
        "value":"1.83",
        "unit":""
    },
    {
        "key":"12",
        "name":"12月",
        "value":"5",
        "unit":""
    }
]